divopt/__init__.py
divopt/test.py
divopt-0.0.3.dist-info/METADATA
divopt-0.0.3.dist-info/WHEEL
divopt-0.0.3.dist-info/top_level.txt
divopt-0.0.3.dist-info/RECORD
