Metadata-Version: 2.1
Name: divopt
Version: 0.0.3
Summary: optimization tools based on domain division
Home-page: https://github.co.jp/
Author: bib_inf
Author-email: contact.bibinf@gmail.com
License: CC0 v1.0
Platform: UNKNOWN
Classifier: Programming Language :: Python :: 3
Classifier: License :: CC0 1.0 Universal (CC0 1.0) Public Domain Dedication
Requires-Dist: relpath
Requires-Dist: ezpip
Requires-Dist: sout
Requires-Dist: numpy
Requires-Dist: tqdm
